wimd/__init__.py
wimd-0.2.dist-info/LICENSE.md
wimd-0.2.dist-info/METADATA
wimd-0.2.dist-info/WHEEL
wimd-0.2.dist-info/top_level.txt
wimd-0.2.dist-info/RECORD
